Workbook

Sheet Instructions
A1: Campaign Performance Report - Excel Version
A2: Replicates HTML Campaign Report Generator with Excel-native controls
A4: 1. GETTING STARTED
A5: 1.1 Import your Sponsored Products Campaign Report CSV into the 'Campaign Data' sheet
A6: 1.2 Import your Business Report CSV into the 'Business Data' sheet (required for TACOS)
A7: 1.3 Set your date range in the 'Settings' sheet
A8: 1.4 Use the Portfolio dropdown to switch between Overall, JN, and Non-JN views
A9: 1.5 Use the Time Period dropdown to switch between Daily, Weekly, and Monthly views
A11: 2. SHEET OVERVIEW
A12: Sheet Name | B12: Description
A13: Dashboard | B13: Main control panel with KPIs and portfolio selection
A14: Executive Summary | B14: Key metrics with month-over-month comparisons
A15: Segment Performance | B15: Branded/Competitor/Non-Branded breakdown
A16: Performance Trends | B16: Daily/Weekly/Monthly trend analysis
A17: Monthly Analysis | B17: Month-over-month performance data
A18: Weekly Analysis | B18: Week-over-week performance data
A19: Organic vs Paid | B19: Total Sales breakdown (requires Business Report)
A20: JN Portfolio | B20: JN-specific metrics and segments
A21: Non-JN Portfolio | B21: Non-JN-specific metrics and segments
A22: Pivot - Portfolio | B22: Cross-tabulation by portfolio and time
A23: Pivot - Segment | B23: Cross-tabulation by segment and time
... A26: Settings | B26: Configuration and dropdown values
A28: 3. INTERACTIVE CONTROLS
A29: Control | B29: Options | C29: Effect
A30: Portfolio Toggle | B30: Overall | JN | Non-JN | C30: Filters all metrics by portfolio
A31: Time Period | B31: Daily | Weekly | Monthly | C31: Aggregates trend data by time period
A32: Start Date | B32: Date picker | C32: Beginning of analysis period
A33: End Date | B33: Date picker | C33: End of analysis period
A35: 4. KEY METRICS DEFINITIONS
A36: Metric | B36: Definition
A37: Ad Spend | B37: Total advertising spend
A38: Ad Sales | B38: Sales attributed to advertising (7-day attribution)
A39: ROAS | B39: Return on Ad Spend = Ad Sales / Ad Spend
A40: ACoS | B40: Advertising Cost of Sale = Ad Spend / Ad Sales × 100%
A41: TACOS | B41: Total Advertising Cost of Sale = Ad Spend / Total Sales × 100%
A42: CVR | B42: Conversion Rate = Orders / Clicks × 100%
A43: CPC | B43: Cost Per Click = Ad Spend / Clicks
A44: CTR | B44: Click-Through Rate = Clicks / Impressions × 100%
A45: Organic Sales | B45: Total Sales - Ad Sales
A48: Made by Krell for Piping Rock

Sheet Dashboard
A1: CAMPAIGN PERFORMANCE REPORT
A2: Executive Dashboard
A3: Date Range: | B3: =Settings!B6 | C3: to | D3: =Settings!B7
A5: CONTROLS
A6: Portfolio: | B6: =Settings!B4 | C6: Time Period: | D6: =Settings!B5
A8: TOTAL AD SALES
A9: =SUMIFS('Campaign Data'!X:X,'Campaign Data'!A:A,">="&Settings!B6,'Campaign Data'!A:A,"<="&Settings!B7,'Campaign Data'!Y:Y,IF(Settings!B4="Overall","*",IF(Settings!B4="JN","JN","Non-JN")))
A11: AD SPEND | C11: AD SALES | E11: ROAS | G11: TACOS
A12: =SUMIFS('Campaign Data'!G:G,'Campaign Data'!A:A,">="&Settings!B6,'Campaign Data'!A:A,"<="&Settings!B7) | C12: =SUMIFS('Campaign Data'!H:H,'Campaign Data'!A:A,">="&Settings!B6,'Campaign Data'!A:A,"<="&Settings!B7) | E12: =IF(A12>0,B12/A12,0) | G12: =IF(SUMIFS('Business Data'!B:B,'Business Data'!A:A,">="&Settings!B6,'Business Data'!A:A,"<="&Settings!B7)>0,A12/SUMIFS('Business Data'!B:B,'Business Data'!A:A,">="&Settings!B6,'Business Data'!A:A,"<="&Settings!B7),0)
A14: SALES BREAKDOWN
A15: Total Sales | B15: Ad Sales | C15: Ad % | D15: Organic Sales | E15: Organic %
A16: =SUMIFS('Business Data'!B:B,'Business Data'!A:A,">="&Settings!B6,'Business Data'!A:A,"<="&Settings!B7) | B16: =B12 | C16: =IF(A16>0,B16/A16,0) | D16: =A16-B16 | E16: =IF(A16>0,D16/A16,0)
A18: SEGMENT PERFORMANCE (Current Period)
A19: Segment | B19: Spend | C19: Sales | D19: ROAS | E19: ACoS
A20: Branded | B20: =SUMIFS('Campaign Data'!Q:Q,'Campaign Data'!A:A,">="&Settings!B6,'Campaign Data'!A:A,"<="&Settings!B7,'Campaign Data'!Z:Z,"Branded") | C20: =SUMIFS('Campaign Data'!X:X,'Campaign Data'!A:A,">="&Settings!B6,'Campaign Data'!A:A,"<="&Settings!B7,'Campaign Data'!Z:Z,"Branded") | D20: =IF(B20>0,C20/B20,0) | E20: =IF(C20>0,B20/C20,0)
A21: Competitor | B21: =SUMIFS('Campaign Data'!Q:Q,'Campaign Data'!A:A,">="&Settings!B6,'Campaign Data'!A:A,"<="&Settings!B7,'Campaign Data'!Z:Z,"Competitor") | C21: =SUMIFS('Campaign Data'!X:X,'Campaign Data'!A:A,">="&Settings!B6,'Campaign Data'!A:A,"<="&Settings!B7,'Campaign Data'!Z:Z,"Competitor") | D21: =IF(B21>0,C21/B21,0) | E21: =IF(C21>0,B21/C21,0)
A22: Non-Branded | B22: =SUMIFS('Campaign Data'!Q:Q,'Campaign Data'!A:A,">="&Settings!B6,'Campaign Data'!A:A,"<="&Settings!B7,'Campaign Data'!Z:Z,"Non-Branded") | C22: =SUMIFS('Campaign Data'!X:X,'Campaign Data'!A:A,">="&Settings!B6,'Campaign Data'!A:A,"<="&Settings!B7,'Campaign Data'!Z:Z,"Non-Branded") | D22: =IF(B22>0,C22/B22,0) | E22: =IF(C22>0,B22/C22,0)
A25: MONTHLY PERFORMANCE TREND
A26: Month | B26: Spend | C26: Sales | D26: ROAS | E26: MoM Spend % | F26: MoM Sales % | G26: MoM ROAS %
A35: Made by Krell for Piping Rock

Sheet Settings
A1: Report Settings & Configuration
A3: GLOBAL CONTROLS
A4: Portfolio: | B4: Overall
A5: Time Period: | B5: Weekly
A6: Start Date: | B6: 45940.845
A7: End Date: | B7: 46030.845
A10: DROPDOWN OPTIONS (DO NOT MODIFY)
A11: Portfolio Options: | B11: Overall | C11: JN | D11: Non-JN
A12: Time Period Options: | B12: Daily | C12: Weekly | D12: Monthly
A13: Segment Options: | B13: Branded | C13: Competitor | D13: Non-Branded
A16: CALCULATED VALUES
A17: Report Generated: | B17: 46030.845
A18: Date Range Days: | B18: =B7-B6

Sheet Executive Summary
A1: EXECUTIVE SUMMARY
A2: Portfolio: | B2: =Settings!B4 | C2: Period: | D2: =TEXT(Settings!B6,"MMM D, YYYY")&" - "&TEXT(Settings!B7,"MMM D, YYYY")
A3: Showing Most Recent Complete Month
A5: AD SALES
A6: =SUMIFS('Campaign Data'!X:X,'Campaign Data'!AB:AB,TEXT(EOMONTH(Settings!B7,-1)+1,"MMM YYYY")) | E6: =SUMIFS('Campaign Data'!X:X,'Campaign Data'!AB:AB,TEXT(EOMONTH(Settings!B7,-2)+1,"MMM YYYY"))
A7: =IF(A6>0,IF(E6>0,(A6-E6)/E6,0),0)
A9: AD SPEND | C9: AD SALES | E9: ROAS | G9: TACOS
A10: =SUMIFS('Campaign Data'!Q:Q,'Campaign Data'!R:R,TEXT(EOMONTH(Settings!B7,-1)+1,"MMM YYYY")) | C10: =SUMIFS('Campaign Data'!X:X,'Campaign Data'!R:R,TEXT(EOMONTH(Settings!B7,-1)+1,"MMM YYYY")) | E10: =IF(A10>0,C10/A10,0) | G10: =IF(SUMIFS('Business Data'!B:B,'Business Data'!I:I,TEXT(EOMONTH(Settings!B7,-1)+1,"MMM YYYY"))>0,A10/SUMIFS('Business Data'!B:B,'Business Data'!I:I,TEXT(EOMONTH(Settings!B7,-1)+1,"MMM YYYY")),0)
A13: SALES BREAKDOWN (Monthly)
A14: Total Sales | B14: Ad Sales | C14: Organic Sales | D14: Ad % | E14: Organic %
A15: =SUMIFS('Business Data'!B:B,'Business Data'!I:I,TEXT(EOMONTH(Settings!B7,-1)+1,"MMM YYYY")) | B15: =C10 | C15: =MAX(0,A15-B15) | D15: =IF(A15>0,B15/A15,0) | E15: =IF(A15>0,C15/A15,0)
A18: KEY INSIGHTS
A19: 1. Ad Sales performance vs previous month shows trend direction
A20: 2. Best performing segment by ROAS indicates optimization opportunities
A21: 3. TACOS trend indicates overall advertising efficiency vs total revenue
A23: MONTHLY PERFORMANCE
A24: Metric | B24: Month -5 | C24: Month -4 | D24: Month -3 | E24: Month -2 | F24: Month -1 | G24: Current
A25: Ad Spend
A26: Ad Sales
A27: ROAS
A28: ACoS %
A29: Orders
A30: Clicks
A31: CVR %

Sheet Segment Performance
A1: SEGMENT PERFORMANCE
A2: Branded / Competitor / Non-Branded Breakdown
A4: PERFORMANCE BY SEGMENT
A5: Segment | B5: Spend | C5: Spend % | D5: Sales | E5: Sales % | F5: ROAS | G5: ACoS | H5: MoM Spend | I5: MoM Sales
A6: Branded | B6: =SUMIFS('Campaign Data'!Q:Q,'Campaign Data'!A:A,">="&Settings!B6,'Campaign Data'!A:A,"<="&Settings!B7,'Campaign Data'!Z:Z,"Branded") | C6: =IF(SUM(B6:B8)>0,B6/SUM(B6:B8),0) | D6: =SUMIFS('Campaign Data'!X:X,'Campaign Data'!A:A,">="&Settings!B6,'Campaign Data'!A:A,"<="&Settings!B7,'Campaign Data'!Z:Z,"Branded") | E6: =IF(SUM(D6:D8)>0,D6/SUM(D6:D8),0) | F6: =IF(B6>0,D6/B6,0) | G6: =IF(D6>0,B6/D6,0)
A7: Competitor | B7: =SUMIFS('Campaign Data'!Q:Q,'Campaign Data'!A:A,">="&Settings!B6,'Campaign Data'!A:A,"<="&Settings!B7,'Campaign Data'!Z:Z,"Competitor") | C7: =IF(SUM(B6:B8)>0,B7/SUM(B6:B8),0) | D7: =SUMIFS('Campaign Data'!X:X,'Campaign Data'!A:A,">="&Settings!B6,'Campaign Data'!A:A,"<="&Settings!B7,'Campaign Data'!Z:Z,"Competitor") | E7: =IF(SUM(D6:D8)>0,D7/SUM(D6:D8),0) | F7: =IF(B7>0,D7/B7,0) | G7: =IF(D7>0,B7/D7,0)
A8: Non-Branded | B8: =SUMIFS('Campaign Data'!Q:Q,'Campaign Data'!A:A,">="&Settings!B6,'Campaign Data'!A:A,"<="&Settings!B7,'Campaign Data'!Z:Z,"Non-Branded") | C8: =IF(SUM(B6:B8)>0,B8/SUM(B6:B8),0) | D8: =SUMIFS('Campaign Data'!X:X,'Campaign Data'!A:A,">="&Settings!B6,'Campaign Data'!A:A,"<="&Settings!B7,'Campaign Data'!Z:Z,"Non-Branded") | E8: =IF(SUM(D6:D8)>0,D8/SUM(D6:D8),0) | F8: =IF(B8>0,D8/B8,0) | G8: =IF(D8>0,B8/D8,0)
A9: TOTAL | B9: =SUM(B6:B8) | C9: 100% | D9: =SUM(D6:D8) | E9: 100% | F9: =IF(B9>0,D9/B9,0) | G9: =IF(D9>0,B9/D9,0)
A12: SEGMENT BY PORTFOLIO
A13: Segment | B13: JN Spend | C13: JN Sales | D13: JN ROAS | E13: Non-JN Spend | F13: Non-JN Sales | G13: Non-JN ROAS
A14: Branded | B14: =SUMIFS('Campaign Data'!Q:Q,'Campaign Data'!A:A,">="&Settings!B6,'Campaign Data'!A:A,"<="&Settings!B7,'Campaign Data'!Z:Z,"Branded",'Campaign Data'!Y:Y,"JN") | C14: =SUMIFS('Campaign Data'!X:X,'Campaign Data'!A:A,">="&Settings!B6,'Campaign Data'!A:A,"<="&Settings!B7,'Campaign Data'!Z:Z,"Branded",'Campaign Data'!Y:Y,"JN") | D14: =IF(B14>0,C14/B14,0) | E14: =SUMIFS('Campaign Data'!Q:Q,'Campaign Data'!A:A,">="&Settings!B6,'Campaign Data'!A:A,"<="&Settings!B7,'Campaign Data'!Z:Z,"Branded",'Campaign Data'!Y:Y,"Non-JN") | F14: =SUMIFS('Campaign Data'!X:X,'Campaign Data'!A:A,">="&Settings!B6,'Campaign Data'!A:A,"<="&Settings!B7,'Campaign Data'!Z:Z,"Branded",'Campaign Data'!Y:Y,"Non-JN") | G14: =IF(E14>0,F14/E14,0)
A15: Competitor | B15: =SUMIFS('Campaign Data'!Q:Q,'Campaign Data'!A:A,">="&Settings!B6,'Campaign Data'!A:A,"<="&Settings!B7,'Campaign Data'!Z:Z,"Competitor",'Campaign Data'!Y:Y,"JN") | C15: =SUMIFS('Campaign Data'!X:X,'Campaign Data'!A:A,">="&Settings!B6,'Campaign Data'!A:A,"<="&Settings!B7,'Campaign Data'!Z:Z,"Competitor",'Campaign Data'!Y:Y,"JN") | D15: =IF(B15>0,C15/B15,0) | E15: =SUMIFS('Campaign Data'!Q:Q,'Campaign Data'!A:A,">="&Settings!B6,'Campaign Data'!A:A,"<="&Settings!B7,'Campaign Data'!Z:Z,"Competitor",'Campaign Data'!Y:Y,"Non-JN") | F15: =SUMIFS('Campaign Data'!X:X,'Campaign Data'!A:A,">="&Settings!B6,'Campaign Data'!A:A,"<="&Settings!B7,'Campaign Data'!Z:Z,"Competitor",'Campaign Data'!Y:Y,"Non-JN") | G15: =IF(E15>0,F15/E15,0)
A16: Non-Branded | B16: =SUMIFS('Campaign Data'!Q:Q,'Campaign Data'!A:A,">="&Settings!B6,'Campaign Data'!A:A,"<="&Settings!B7,'Campaign Data'!Z:Z,"Non-Branded",'Campaign Data'!Y:Y,"JN") | C16: =SUMIFS('Campaign Data'!X:X,'Campaign Data'!A:A,">="&Settings!B6,'Campaign Data'!A:A,"<="&Settings!B7,'Campaign Data'!Z:Z,"Non-Branded",'Campaign Data'!Y:Y,"JN") | D16: =IF(B16>0,C16/B16,0) | E16: =SUMIFS('Campaign Data'!Q:Q,'Campaign Data'!A:A,">="&Settings!B6,'Campaign Data'!A:A,"<="&Settings!B7,'Campaign Data'!Z:Z,"Non-Branded",'Campaign Data'!Y:Y,"Non-JN") | F16: =SUMIFS('Campaign Data'!X:X,'Campaign Data'!A:A,">="&Settings!B6,'Campaign Data'!A:A,"<="&Settings!B7,'Campaign Data'!Z:Z,"Non-Branded",'Campaign Data'!Y:Y,"Non-JN") | G16: =IF(E16>0,F16/E16,0)

Sheet Performance Trends
A1: PERFORMANCE TRENDS
A2: Time Period: | B2: =Settings!B5 | C2: Portfolio: | D2: =Settings!B4
A4: WEEKLY PERFORMANCE
A5: Week | B5: Spend | C5: Sales | D5: ROAS | E5: ACoS | F5: WoW Spend % | G5: WoW Sales % | H5: WoW ROAS %
A20: MONTHLY PERFORMANCE
A21: Month | B21: Spend | C21: Sales | D21: ROAS | E21: ACoS | F21: Orders | G21: Clicks | H21: CVR | I21: MoM Spend | J21: MoM Sales
A36: SEGMENT TRENDS BY MONTH
A38: Branded
A48: Competitor
A58: Non-Branded

Sheet Monthly Analysis
A1: MONTH-OVER-MONTH ANALYSIS
A3: Month | B3: Spend | C3: Spend Chg | D3: Spend % | E3: Sales | F3: Sales Chg | G3: Sales % | H3: ROAS | I3: ROAS Chg | J3: ACoS

Sheet Weekly Analysis
A1: WEEK-OVER-WEEK ANALYSIS
A3: Week | B3: Date Range | C3: Spend | D3: Spend Chg | E3: Spend % | F3: Sales | G3: Sales Chg | H3: Sales % | I3: ROAS | J3: ACoS | K3: Orders

Sheet Organic vs Paid
A1: ORGANIC VS PAID ANALYSIS
A2: Requires Business Report data for Total Sales
A4: PERIOD SUMMARY
A5: Total Sales | B5: Ad Sales | C5: Organic Sales | D5: Ad % | E5: Organic % | F5: TACOS
A6: =SUMIFS('Business Data'!B:B,'Business Data'!A:A,">="&Settings!B6,'Business Data'!A:A,"<="&Settings!B7) | B6: =SUMIFS('Campaign Data'!X:X,'Campaign Data'!A:A,">="&Settings!B6,'Campaign Data'!A:A,"<="&Settings!B7) | C6: =MAX(0,A6-B6) | D6: =IF(A6>0,B6/A6,0) | E6: =IF(A6>0,C6/A6,0) | F6: =IF(A6>0,SUMIFS('Campaign Data'!Q:Q,'Campaign Data'!A:A,">="&Settings!B6,'Campaign Data'!A:A,"<="&Settings!B7)/A6,0)
A9: MONTHLY ORGANIC VS PAID
A10: Month | B10: Total Sales | C10: Ad Sales | D10: Organic Sales | E10: Organic % | F10: Organic Chg | G10: Ad Sales Chg | H10: TACOS

Sheet JN Portfolio
A1: JN PORTFOLIO ANALYSIS
A3: PORTFOLIO SUMMARY
A4: Spend | B4: Sales | C4: ROAS | D4: ACoS | E4: Orders | F4: Clicks | G4: CVR
A5: =SUMIFS('Campaign Data'!Q:Q,'Campaign Data'!A:A,">="&Settings!B6,'Campaign Data'!A:A,"<="&Settings!B7,'Campaign Data'!Y:Y,"JN") | B5: =SUMIFS('Campaign Data'!X:X,'Campaign Data'!A:A,">="&Settings!B6,'Campaign Data'!A:A,"<="&Settings!B7,'Campaign Data'!Y:Y,"JN") | C5: =IF(A5>0,B5/A5,0) | D5: =IF(B5>0,A5/B5,0) | E5: =SUMIFS('Campaign Data'!U:U,'Campaign Data'!A:A,">="&Settings!B6,'Campaign Data'!A:A,"<="&Settings!B7,'Campaign Data'!Y:Y,"JN") | F5: =SUMIFS('Campaign Data'!N:N,'Campaign Data'!A:A,">="&Settings!B6,'Campaign Data'!A:A,"<="&Settings!B7,'Campaign Data'!Y:Y,"JN") | G5: =IF(F5>0,E5/F5,0)
A8: SEGMENT BREAKDOWN
A9: Segment | B9: Spend | C9: Sales | D9: ROAS | E9: ACoS
A10: Branded | B10: =SUMIFS('Campaign Data'!Q:Q,'Campaign Data'!A:A,">="&Settings!B6,'Campaign Data'!A:A,"<="&Settings!B7,'Campaign Data'!Y:Y,"JN",'Campaign Data'!Z:Z,"Branded") | C10: =SUMIFS('Campaign Data'!X:X,'Campaign Data'!A:A,">="&Settings!B6,'Campaign Data'!A:A,"<="&Settings!B7,'Campaign Data'!Y:Y,"JN",'Campaign Data'!Z:Z,"Branded") | D10: =IF(B10>0,C10/B10,0) | E10: =IF(C10>0,B10/C10,0)
A11: Competitor | B11: =SUMIFS('Campaign Data'!Q:Q,'Campaign Data'!A:A,">="&Settings!B6,'Campaign Data'!A:A,"<="&Settings!B7,'Campaign Data'!Y:Y,"JN",'Campaign Data'!Z:Z,"Competitor") | C11: =SUMIFS('Campaign Data'!X:X,'Campaign Data'!A:A,">="&Settings!B6,'Campaign Data'!A:A,"<="&Settings!B7,'Campaign Data'!Y:Y,"JN",'Campaign Data'!Z:Z,"Competitor") | D11: =IF(B11>0,C11/B11,0) | E11: =IF(C11>0,B11/C11,0)
A12: Non-Branded | B12: =SUMIFS('Campaign Data'!Q:Q,'Campaign Data'!A:A,">="&Settings!B6,'Campaign Data'!A:A,"<="&Settings!B7,'Campaign Data'!Y:Y,"JN",'Campaign Data'!Z:Z,"Non-Branded") | C12: =SUMIFS('Campaign Data'!X:X,'Campaign Data'!A:A,">="&Settings!B6,'Campaign Data'!A:A,"<="&Settings!B7,'Campaign Data'!Y:Y,"JN",'Campaign Data'!Z:Z,"Non-Branded") | D12: =IF(B12>0,C12/B12,0) | E12: =IF(C12>0,B12/C12,0)

Sheet Non-JN Portfolio
A1: Non-JN PORTFOLIO ANALYSIS
A3: PORTFOLIO SUMMARY
A4: Spend | B4: Sales | C4: ROAS | D4: ACoS | E4: Orders | F4: Clicks | G4: CVR
A5: =SUMIFS('Campaign Data'!Q:Q,'Campaign Data'!A:A,">="&Settings!B6,'Campaign Data'!A:A,"<="&Settings!B7,'Campaign Data'!Y:Y,"Non-JN") | B5: =SUMIFS('Campaign Data'!X:X,'Campaign Data'!A:A,">="&Settings!B6,'Campaign Data'!A:A,"<="&Settings!B7,'Campaign Data'!Y:Y,"Non-JN") | C5: =IF(A5>0,B5/A5,0) | D5: =IF(B5>0,A5/B5,0) | E5: =SUMIFS('Campaign Data'!U:U,'Campaign Data'!A:A,">="&Settings!B6,'Campaign Data'!A:A,"<="&Settings!B7,'Campaign Data'!Y:Y,"Non-JN") | F5: =SUMIFS('Campaign Data'!N:N,'Campaign Data'!A:A,">="&Settings!B6,'Campaign Data'!A:A,"<="&Settings!B7,'Campaign Data'!Y:Y,"Non-JN") | G5: =IF(F5>0,E5/F5,0)
A8: SEGMENT BREAKDOWN
A9: Segment | B9: Spend | C9: Sales | D9: ROAS | E9: ACoS
A10: Branded | B10: =SUMIFS('Campaign Data'!Q:Q,'Campaign Data'!A:A,">="&Settings!B6,'Campaign Data'!A:A,"<="&Settings!B7,'Campaign Data'!Y:Y,"Non-JN",'Campaign Data'!Z:Z,"Branded") | C10: =SUMIFS('Campaign Data'!X:X,'Campaign Data'!A:A,">="&Settings!B6,'Campaign Data'!A:A,"<="&Settings!B7,'Campaign Data'!Y:Y,"Non-JN",'Campaign Data'!Z:Z,"Branded") | D10: =IF(B10>0,C10/B10,0) | E10: =IF(C10>0,B10/C10,0)
A11: Competitor | B11: =SUMIFS('Campaign Data'!Q:Q,'Campaign Data'!A:A,">="&Settings!B6,'Campaign Data'!A:A,"<="&Settings!B7,'Campaign Data'!Y:Y,"Non-JN",'Campaign Data'!Z:Z,"Competitor") | C11: =SUMIFS('Campaign Data'!X:X,'Campaign Data'!A:A,">="&Settings!B6,'Campaign Data'!A:A,"<="&Settings!B7,'Campaign Data'!Y:Y,"Non-JN",'Campaign Data'!Z:Z,"Competitor") | D11: =IF(B11>0,C11/B11,0) | E11: =IF(C11>0,B11/C11,0)
A12: Non-Branded | B12: =SUMIFS('Campaign Data'!Q:Q,'Campaign Data'!A:A,">="&Settings!B6,'Campaign Data'!A:A,"<="&Settings!B7,'Campaign Data'!Y:Y,"Non-JN",'Campaign Data'!Z:Z,"Non-Branded") | C12: =SUMIFS('Campaign Data'!X:X,'Campaign Data'!A:A,">="&Settings!B6,'Campaign Data'!A:A,"<="&Settings!B7,'Campaign Data'!Y:Y,"Non-JN",'Campaign Data'!Z:Z,"Non-Branded") | D12: =IF(B12>0,C12/B12,0) | E12: =IF(C12>0,B12/C12,0)

Sheet Pivot - Portfolio
A1: SPEND BY MONTH & PORTFOLIO TYPE
A3: Month | B3: JN | C3: Non-JN | D3: Total
A18: AD SALES BY MONTH & PORTFOLIO TYPE
A20: Month | B20: JN | C20: Non-JN | D20: Total
A35: ROAS BY MONTH & PORTFOLIO TYPE
A37: Month | B37: JN | C37: Non-JN | D37: Total

Sheet Pivot - Segment
A1: SPEND BY MONTH & SEGMENT
A3: Month | B3: Branded | C3: Competitor | D3: Non-Branded | E3: Total
A18: AD SALES BY MONTH & SEGMENT
A20: Month | B20: Branded | C20: Competitor | D20: Non-Branded | E20: Total
A35: ROAS BY MONTH & SEGMENT
A37: Month | B37: Branded | C37: Competitor | D37: Non-Branded | E37: Total

Sheet Campaign Data
A1: PASTE YOUR SPONSORED PRODUCTS CAMPAIGN REPORT DATA BELOW
A2: Format: Copy all data including headers from your CSV export (row 4 shows expected columns)
A3: Key columns: A=Date, B=Portfolio, D=Campaign, L=Impressions, N=Clicks, Q=Spend, X=Sales, U=Orders
A4: Date | B4: Portfolio name | C4: Program Type | D4: Campaign Name | E4: Retailer | F4: Country | G4: Status | H4: Currency | I4: Budget Amount | J4: Targeting Type | K4: Bidding strategy | L4: Impressions | M4: Last Year Impressions | N4: Clicks | O4: Last Year Clicks | P4: Click-Thru Rate (CTR) | Q4: Spend | R4: Last Year Spend | S4: Cost Per Click (CPC) | T4: Last Year Cost Per Click (CPC) | U4: 7 Day Total Orders (#) | V4: Total Advertising Cost of Sales (ACOS) | W4: Total Return on Advertising Spend (ROAS) | X4: 7 Day Total Sales | Y4: Portfolio Type | Z4: Segment | AA4: Week | AB4: Month

Sheet Business Data
A1: PASTE YOUR BUSINESS REPORT DATA BELOW
A2: Required for TACOS calculation and Organic vs Paid analysis
A3: Key columns: A=Date, B=Ordered Product Sales (Total Sales), D=Units Ordered, N=Sessions
A4: Date | B4: Ordered Product Sales | C4: Ordered Product Sales - B2B | D4: Units Ordered | E4: Units Ordered - B2B | F4: Total Order Items | G4: Total Order Items - B2B | H4: Average Sales per Order Item | I4: Average Sales per Order Item - B2B | J4: Average Units per Order Item | K4: Average Units per Order Item - B2B | L4: Average Selling Price | M4: Average Selling Price - B2B | N4: Sessions - Total | O4: Sessions - Total - B2B | P4: Order Item Session Percentage | Q4: Order Item Session Percentage - B2B | R4: Average Offer Count | S4: Week | T4: Month
